stochasticprocess/__init__.py
stochasticprocess/poisson.py
stochasticprocess/version.py
stochasticprocess-0.2.0.dist-info/METADATA
stochasticprocess-0.2.0.dist-info/WHEEL
stochasticprocess-0.2.0.dist-info/top_level.txt
stochasticprocess-0.2.0.dist-info/RECORD
