Metadata-Version: 2.1
Name: stochasticprocess
Version: 0.2.0
Summary: Stochastic Process
Home-page: http://github.com/zhiqingxiao/stochasticprocess/
Author: Zhiqing Xiao
Author-email: xzq.xiaozhiqing@gmail.com
Classifier: Programming Language :: Python
Classifier: Intended Audience :: Science/Research
